instana/__init__.py
instana/__main__.py
instana/configurator.py
instana/fsm.py
instana/helpers.py
instana/log.py
instana/middleware.py
instana/options.py
instana/recorder.py
instana/sampling.py
instana/singletons.py
instana/span_context.py
instana/tracer.py
instana/version.py
instana/wsgi.py
instana/agent/__init__.py
instana/agent/aws_eks_fargate.py
instana/agent/aws_fargate.py
instana/agent/aws_lambda.py
instana/agent/base.py
instana/agent/google_cloud_run.py
instana/agent/host.py
instana/autoprofile/__init__.py
instana/autoprofile/frame_cache.py
instana/autoprofile/profile.py
instana/autoprofile/profiler.py
instana/autoprofile/runtime.py
instana/autoprofile/sampler_scheduler.py
instana/autoprofile/schedule.py
instana/autoprofile/samplers/__init__.py
instana/autoprofile/samplers/allocation_sampler.py
instana/autoprofile/samplers/block_sampler.py
instana/autoprofile/samplers/cpu_sampler.py
instana/collector/__init__.py
instana/collector/aws_eks_fargate.py
instana/collector/aws_fargate.py
instana/collector/aws_lambda.py
instana/collector/base.py
instana/collector/google_cloud_run.py
instana/collector/host.py
instana/collector/utils.py
instana/collector/helpers/__init__.py
instana/collector/helpers/base.py
instana/collector/helpers/process.py
instana/collector/helpers/resource_usage.py
instana/collector/helpers/runtime.py
instana/collector/helpers/eks/__init__.py
instana/collector/helpers/eks/process.py
instana/collector/helpers/fargate/__init__.py
instana/collector/helpers/fargate/container.py
instana/collector/helpers/fargate/docker.py
instana/collector/helpers/fargate/process.py
instana/collector/helpers/fargate/task.py
instana/collector/helpers/google_cloud_run/__init__.py
instana/collector/helpers/google_cloud_run/instance_entity.py
instana/collector/helpers/google_cloud_run/process.py
instana/hooks/__init__.py
instana/hooks/hook_gunicorn.py
instana/instrumentation/__init__.py
instana/instrumentation/aio_pika.py
instana/instrumentation/aioamqp.py
instana-3.10.0.dist-info/METADATA
instana-3.10.0.dist-info/WHEEL
instana-3.10.0.dist-info/entry_points.txt
instana-3.10.0.dist-info/licenses/LICENSE
instana-3.10.0.dist-info/RECORD
