Metadata-Version: 2.4
Name: instana
Version: 3.10.0
Summary: Python Distributed Tracing & Metrics Sensor for Instana.
Project-URL: Documentation, https://ibm.biz/monitoring-python
Project-URL: Issues, https://github.com/instana/python-sensor/issues
Project-URL: Source, https://github.com/instana/python-sensor
Author: Instana Team Python Tracer Engineers
License-Expression: MIT
License-File: LICENSE
Keywords: distributed-tracing,metrics,monitoring,opentelemetry,performance,tracing
Classifier: Development Status :: 5 - Production/Stable
Classifier: Intended Audience :: Developers
Classifier: Intended Audience :: Information Technology
Classifier: Intended Audience :: Science/Research
Classifier: Intended Audience :: System Administrators
Classifier: License :: OSI Approved :: MIT License
Classifier: Operating System :: OS Independent
Classifier: Programming Language :: Python
Classifier: Programming Language :: Python :: 3.9
Classifier: Programming Language :: Python :: 3.10
Classifier: Programming Language :: Python :: 3.11
Classifier: Programming Language :: Python :: 3.12
Classifier: Programming Language :: Python :: 3.13
Classifier: Programming Language :: Python :: 3.14
Classifier: Programming Language :: Python :: Implementation :: CPython
Classifier: Topic :: Internet :: WWW/HTTP :: WSGI :: Middleware
Classifier: Topic :: Software Development :: Libraries :: Python Modules
Classifier: Topic :: System :: Monitoring
Classifier: Topic :: System :: Networking :: Monitoring
Requires-Python: >=3.9
Requires-Dist: autowrapt>=1.0
Requires-Dist: fysom>=2.1.2
Requires-Dist: opentelemetry-api>=1.27.0
Requires-Dist: opentelemetry-semantic-conventions>=0.48b0
Requires-Dist: psutil>=5.9.0; sys_platform == 'win32'
Requires-Dist: pyyaml>=6.0.2
Requires-Dist: requests>=2.6.0
Requires-Dist: typing-extensions>=4.12.2
Requires-Dist: urllib3>=1.26.5
Provides-Extra: dev
Requires-Dist: pre-commit>=3.0.0; extra == 'dev'
Requires-Dist: pytest; extra == 'dev'
Requires-Dist: pytest-cov; extra == 'dev'
Requires-Dist: pytest-mock; extra == 'dev'
Requires-Dist: ruff; extra == 'dev'
